utxorpc/__init__.py
utxorpc/cardano.py
utxorpc/generics/__init__.py
utxorpc/generics/clients/__init__.py
utxorpc/generics/clients/sync_client.py
utxorpc-0.1.0.dist-info/LICENSE
utxorpc-0.1.0.dist-info/METADATA
utxorpc-0.1.0.dist-info/WHEEL
utxorpc-0.1.0.dist-info/RECORD
