Metadata-Version: 2.1
Name: utxorpc
Version: 0.1.0
Summary: UTxO RPC SDK.
Home-page: https://github.com/utxorpc/python-sdk
License: Apache-2.0
Author: Felipe Gonzalez
Author-email: felipe@txpipe.io
Requires-Python: >=3.8,<4.0
Classifier: License :: OSI Approved :: Apache Software License
Classifier: Programming Language :: Python :: 3
Classifier: Programming Language :: Python :: 3.8
Classifier: Programming Language :: Python :: 3.9
Classifier: Programming Language :: Python :: 3.10
Classifier: Programming Language :: Python :: 3.11
Classifier: Programming Language :: Python :: 3.12
Requires-Dist: typing-extensions (>=4.12.2,<5.0.0)
Requires-Dist: utxorpc-spec (==0.5.1)
Project-URL: Repository, https://github.com/utxorpc/python-sdk
